extractTool/__init__.py
extractTool/extractTool.py
extractTool/getCSVInfo.py
extractTool/getGeoJsonInfo.py
extractTool/getGeoPackageInfo.py
extractTool/getGeoTiffInfo.py
extractTool/getIsoInfo.py
extractTool/getNetCDFInfo.py
extractTool/getShapefileInfo.py
extractTool/getTimeextent.py
extractTool/mastersim.py
extractTool/ogr2ogr.py
extractTool/openFolder.py
extractTool/similar.py
extractTool/similar_api.py
extractTool/test_extractTime.py
extractTool/test_getTime.py
extractTool/test_mastersim.py
extractTool/test_similar.py
extractTool/test_single.py
extractTool/test_whole.py
extractTool-0.4.9.dist-info/LICENSE
extractTool-0.4.9.dist-info/METADATA
extractTool-0.4.9.dist-info/WHEEL
extractTool-0.4.9.dist-info/entry_points.txt
extractTool-0.4.9.dist-info/top_level.txt
extractTool-0.4.9.dist-info/RECORD
